IS_415_Project/__init__.py
IS_415_Project-0.0.2.dist-info/LICENSE
IS_415_Project-0.0.2.dist-info/METADATA
IS_415_Project-0.0.2.dist-info/WHEEL
IS_415_Project-0.0.2.dist-info/top_level.txt
IS_415_Project-0.0.2.dist-info/RECORD
