Metadata-Version: 2.1
Name: IS-415-Project
Version: 0.0.2
Summary: A package for the IS 415 Project
Home-page: https://github.com/tatertot365/415-Project-Package
Author: Tate Gillespie
Author-email: tate.gillespie@gmail.com
License: MIT
Requires-Python: >=3.8
License-File: LICENSE
